{
  "schema": "OPS_RUN_RECEIPT_V1",
  "run_id": "120a7c5e-81a9-48e1-a7da-5f34ead24da2",
  "asof": "2026-01-11T17:57:41.070978",
  "started_at": "2026-01-11T17:57:41.055671",
  "finished_at": "2026-01-11T17:57:41.070981",
  "overall_status": "DONE",
  "ops_report_ref": "reports/ops/daily/ops_report_latest.json",
  "evidence_health": {
    "decision": "WARN",
    "generated_at": "2026-01-11T17:57:41.059404",
    "latest_ref": "reports/ops/evidence/health/health_latest.json",
    "snapshot_ref": "reports\\ops\\evidence\\health\\snapshots\\health_20260111_175741.json",
    "top_fail_reasons": [],
    "fail_closed_triggered": false,
    "error_summary": null
  },
  "ticket_step": {
    "attempted": false,
    "selected_request_id": null,
    "selected_request_type": null,
    "decision": "NONE",
    "reason": "NO_OPEN_TICKETS",
    "receipt_ref": null
  },
  "safety_snapshot": {
    "emergency_stop_enabled": false,
    "execution_gate_mode": "DRY_RUN",
    "window_active": true,
    "allowlist_version": "1.0"
  },
  "counters": {
    "tickets_open": 0,
    "tickets_in_progress": 1,
    "tickets_done": 14,
    "tickets_failed": 12,
    "tickets_blocked": 8,
    "skips_this_run": 0
  },
  "ops_summary": {
    "decision_observed": "WARN",
    "latest_ref": "reports\\ops\\summary\\ops_summary_latest.json",
    "snapshot_ref": "reports\\ops\\summary\\snapshots\\ops_summary_20260111_175741.json"
  },
  "evidence_refs": [
    "reports\\ops\\summary\\snapshots\\ops_summary_20260111_175741.json",
    "reports/ops/evidence/health/health_latest.json"
  ]
}